medvision_ds/__init__.py
medvision_ds/__version__.py
medvision_ds/datasets/__init__.py
medvision_ds/datasets/ACDC/__init__.py
medvision_ds/datasets/ACDC/download_fast.py
medvision_ds/datasets/ACDC/download_raw.py
medvision_ds/datasets/ACDC/preprocess_detection.py
medvision_ds/datasets/ACDC/preprocess_segmentation.py
medvision_ds/datasets/AMOS22/__init__.py
medvision_ds/datasets/AMOS22/download.py
medvision_ds/datasets/AMOS22/preprocess_detection.py
medvision_ds/datasets/AMOS22/preprocess_segmentation.py
medvision_ds/datasets/AbdomenAtlas__1_0__Mini/__init__.py
medvision_ds/datasets/AbdomenAtlas__1_0__Mini/download_raw.py
medvision_ds/datasets/AbdomenAtlas__1_0__Mini/preprocess_detection.py
medvision_ds/datasets/AbdomenAtlas__1_0__Mini/preprocess_segmentation.py
medvision_ds/datasets/AbdomenCT_1K/__init__.py
medvision_ds/datasets/AbdomenCT_1K/download.py
medvision_ds/datasets/AbdomenCT_1K/preprocess_detection.py
medvision_ds/datasets/AbdomenCT_1K/preprocess_segmentation.py
medvision_ds/datasets/BCV15/__init__.py
medvision_ds/datasets/BCV15/download.py
medvision_ds/datasets/BCV15/preprocess_detection.py
medvision_ds/datasets/BCV15/preprocess_segmentation.py
medvision_ds/datasets/BraTS24/__init__.py
medvision_ds/datasets/BraTS24/download.py
medvision_ds/datasets/BraTS24/preprocess_biometry.py
medvision_ds/datasets/BraTS24/preprocess_detection.py
medvision_ds/datasets/BraTS24/preprocess_segmentation.py
medvision_ds/datasets/CAMUS/__init__.py
medvision_ds/datasets/CAMUS/download_fast.py
medvision_ds/datasets/CAMUS/download_raw.py
medvision_ds/datasets/CAMUS/preprocess_detection.py
medvision_ds/datasets/CAMUS/preprocess_segmentation.py
medvision_ds/datasets/Ceph_Biometrics_400/__init__.py
medvision_ds/datasets/Ceph_Biometrics_400/download_fast.py
medvision_ds/datasets/Ceph_Biometrics_400/download_raw.py
medvision_ds/datasets/Ceph_Biometrics_400/preprocess_biometry.py
medvision_ds/datasets/CrossMoDA/__init__.py
medvision_ds/datasets/CrossMoDA/download_fast.py
medvision_ds-1.0.0.dist-info/METADATA
medvision_ds-1.0.0.dist-info/WHEEL
medvision_ds-1.0.0.dist-info/top_level.txt
medvision_ds-1.0.0.dist-info/RECORD
