Metadata-Version: 2.4
Name: medvision_ds
Version: 1.0.0
Summary: medvision_ds: a codebase for the MedVision dataset
Author-email: Yongcheng Yao <yc.yao@ed.ac.uk>
License: CC-BY-NC 4.0
Project-URL: License, https://creativecommons.org/licenses/by-nc/4.0/
Project-URL: Homepage, https://medvision.github.io
Requires-Python: >=3.9
Requires-Dist: nibabel
Requires-Dist: numpy
Requires-Dist: SimpleITK
Requires-Dist: huggingface_hub[cli,xet]
Requires-Dist: synapseclient
Requires-Dist: gdown
Requires-Dist: gdrive
Requires-Dist: requests
Requires-Dist: scipy
Requires-Dist: opencv-python
Requires-Dist: matplotlib
Requires-Dist: rarfile
Requires-Dist: py7zr
Requires-Dist: scikit-image
Requires-Dist: pynrrd
Requires-Dist: tqdm
Requires-Dist: pandas
Requires-Dist: datasets==3.6.0
